DisCORE/DisCORE.py
DisCORE/__init__.py
DisCORE-0.8.1.dist-info/LICENSE
DisCORE-0.8.1.dist-info/METADATA
DisCORE-0.8.1.dist-info/WHEEL
DisCORE-0.8.1.dist-info/top_level.txt
DisCORE-0.8.1.dist-info/RECORD
