Metadata-Version: 2.1
Name: DisCORE
Version: 0.8.1
Summary: A library of scripts for manipulating data and webhooks
Home-page: https://github.com/LDShadowLord/DisCORE
Author: LDShadowLord
Author-email: ldshadowlord@gmail.com
License: UNKNOWN
Platform: UNKNOWN
Classifier: Programming Language :: Python :: 3
Classifier: License :: OSI Approved :: MIT License
Classifier: Operating System :: OS Independent
Requires-Python: >=3.8
